<?xml version="1.0" encoding="UTF-8"?>
<pc:PcGts xmlns:pc="http://schema.primaresearch.org/PAGE/gts/pagecontent/2019-07-15" xmlns:xsi="http://www.w3.org/2001/XMLSchema-instance" xsi:schemaLocation="http://schema.primaresearch.org/PAGE/gts/pagecontent/2019-07-15 http://schema.primaresearch.org/PAGE/gts/pagecontent/2019-07-15/pagecontent.xsd" pcGtsId="FILE_0012_OCR-D-OCR">
    <pc:Metadata>
        <pc:Creator>OCR-D/core 2.24.0</pc:Creator>
        <pc:Created>2021-05-03T16:12:45.532059</pc:Created>
        <pc:LastChange>2021-05-03T16:12:45.532059</pc:LastChange>
        <pc:MetadataItem type="processingStep" name="preprocessing/optimization/binarization" value="ocrd-cis-ocropy-binarize">
            <pc:Labels externalModel="ocrd-tool" externalId="parameters">
                <pc:Label value="ocropy" type="method"/>
                <pc:Label value="0.5" type="threshold"/>
                <pc:Label value="False" type="grayscale"/>
                <pc:Label value="0.0" type="maxskew"/>
                <pc:Label value="0" type="noise_maxsize"/>
                <pc:Label value="0" type="dpi"/>
                <pc:Label value="page" type="level-of-operation"/>
            </pc:Labels>
            <pc:Labels externalModel="ocrd-tool" externalId="version">
                <pc:Label value="0.1.5" type="ocrd-cis-ocropy-binarize"/>
                <pc:Label value="2.24.0" type="ocrd/core"/>
            </pc:Labels>
        </pc:MetadataItem>
        <pc:MetadataItem type="processingStep" name="preprocessing/optimization/cropping" value="ocrd-anybaseocr-crop">
            <pc:Labels externalModel="ocrd-tool" externalId="parameters">
                <pc:Label value="0" type="dpi"/>
                <pc:Label value="50.0" type="rulerRatioMax"/>
                <pc:Label value="3.0" type="rulerRatioMin"/>
                <pc:Label value="0.3" type="rulerAreaMax"/>
                <pc:Label value="0.01" type="rulerAreaMin"/>
                <pc:Label value="0.95" type="rulerWidthMax"/>
                <pc:Label value="0.05" type="columnAreaMin"/>
                <pc:Label value="0.04" type="columnSepWidthMax"/>
                <pc:Label value="0.25" type="marginTop"/>
                <pc:Label value="0.75" type="marginBottom"/>
                <pc:Label value="0.3" type="marginLeft"/>
                <pc:Label value="0.7" type="marginRight"/>
                <pc:Label value="10" type="padding"/>
            </pc:Labels>
            <pc:Labels externalModel="ocrd-tool" externalId="version">
                <pc:Label value="1.4.1" type="ocrd-anybaseocr-crop"/>
                <pc:Label value="2.24.0" type="ocrd/core"/>
            </pc:Labels>
        </pc:MetadataItem>
        <pc:MetadataItem type="processingStep" name="preprocessing/optimization/binarization" value="ocrd-skimage-binarize">
            <pc:Labels externalModel="ocrd-tool" externalId="parameters">
                <pc:Label value="li" type="method"/>
                <pc:Label value="page" type="level-of-operation"/>
                <pc:Label value="0" type="dpi"/>
                <pc:Label value="301" type="window_size"/>
                <pc:Label value="0.34" type="k"/>
            </pc:Labels>
            <pc:Labels externalModel="ocrd-tool" externalId="version">
                <pc:Label value="0.1.7" type="ocrd-skimage-binarize"/>
                <pc:Label value="2.24.0" type="ocrd/core"/>
            </pc:Labels>
        </pc:MetadataItem>
        <pc:MetadataItem type="processingStep" name="preprocessing/optimization/despeckling" value="ocrd-skimage-denoise">
            <pc:Labels externalModel="ocrd-tool" externalId="parameters">
                <pc:Label value="page" type="level-of-operation"/>
                <pc:Label value="0" type="dpi"/>
                <pc:Label value="0.0" type="protect"/>
                <pc:Label value="1.0" type="maxsize"/>
            </pc:Labels>
            <pc:Labels externalModel="ocrd-tool" externalId="version">
                <pc:Label value="0.1.7" type="ocrd-skimage-denoise"/>
                <pc:Label value="2.24.0" type="ocrd/core"/>
            </pc:Labels>
        </pc:MetadataItem>
        <pc:MetadataItem type="processingStep" name="preprocessing/optimization/deskewing" value="ocrd-tesserocr-deskew">
            <pc:Labels externalModel="ocrd-tool" externalId="parameters">
                <pc:Label value="page" type="operation_level"/>
                <pc:Label value="0" type="dpi"/>
                <pc:Label value="1.5" type="min_orientation_confidence"/>
            </pc:Labels>
            <pc:Labels externalModel="ocrd-tool" externalId="version">
                <pc:Label value="0.12.0" type="ocrd-tesserocr-deskew"/>
                <pc:Label value="2.24.0" type="ocrd/core"/>
            </pc:Labels>
        </pc:MetadataItem>
        <pc:MetadataItem type="processingStep" name="layout/segmentation/region" value="ocrd-cis-ocropy-segment">
            <pc:Labels externalModel="ocrd-tool" externalId="parameters">
                <pc:Label value="page" type="level-of-operation"/>
                <pc:Label value="0" type="dpi"/>
                <pc:Label value="20" type="maxcolseps"/>
                <pc:Label value="20" type="maxseps"/>
                <pc:Label value="10" type="maximages"/>
                <pc:Label value="4" type="csminheight"/>
                <pc:Label value="10" type="hlminwidth"/>
                <pc:Label value="0.01" type="gap_height"/>
                <pc:Label value="1.5" type="gap_width"/>
                <pc:Label value="True" type="overwrite_order"/>
                <pc:Label value="True" type="overwrite_separators"/>
                <pc:Label value="True" type="overwrite_regions"/>
                <pc:Label value="True" type="overwrite_lines"/>
                <pc:Label value="2.4" type="spread"/>
            </pc:Labels>
            <pc:Labels externalModel="ocrd-tool" externalId="version">
                <pc:Label value="0.1.5" type="ocrd-cis-ocropy-segment"/>
                <pc:Label value="2.24.0" type="ocrd/core"/>
            </pc:Labels>
        </pc:MetadataItem>
        <pc:MetadataItem type="processingStep" name="preprocessing/optimization/dewarping" value="ocrd-cis-ocropy-dewarp">
            <pc:Labels externalModel="ocrd-tool" externalId="parameters">
                <pc:Label value="0" type="dpi"/>
                <pc:Label value="4.0" type="range"/>
                <pc:Label value="1.0" type="smoothness"/>
                <pc:Label value="0.05" type="max_neighbour"/>
            </pc:Labels>
            <pc:Labels externalModel="ocrd-tool" externalId="version">
                <pc:Label value="0.1.5" type="ocrd-cis-ocropy-dewarp"/>
                <pc:Label value="2.24.0" type="ocrd/core"/>
            </pc:Labels>
        </pc:MetadataItem>
        <pc:MetadataItem type="processingStep" name="recognition/text-recognition" value="ocrd-calamari-recognize">
            <pc:Labels externalModel="ocrd-tool" externalId="parameters">
                <pc:Label value="qurator-gt4histocr-1.0" type="checkpoint_dir"/>
                <pc:Label value="confidence_voter_default_ctc" type="voter"/>
                <pc:Label value="line" type="textequiv_level"/>
                <pc:Label value="0.001" type="glyph_conf_cutoff"/>
                <pc:Label value="/home/kba/.local/share/ocrd-resources/ocrd-calamari-recognize/qurator-gt4histocr-1.0/*.ckpt.json" type="checkpoint"/>
            </pc:Labels>
        </pc:MetadataItem>
    </pc:Metadata>
    <pc:Page imageFilename="DEFAULT/FILE_0012_DEFAULT.jpg" imageWidth="800" imageHeight="1185" orientation="0.44958407534628" readingDirection="left-to-right" textLineOrder="top-to-bottom">
        <pc:AlternativeImage filename="OCR-D-BIN/FILE_0012_OCR-D-BIN.IMG-BIN.png" comments=",binarized"/>
        <pc:AlternativeImage filename="OCR-D-CROP/FILE_0012_OCR-D-CROP.IMG-CROP.png" comments=",binarized,cropped"/>
        <pc:AlternativeImage filename="OCR-D-BIN2/FILE_0012_OCR-D-BIN2.IMG-BIN.png" comments=",cropped,binarized"/>
        <pc:AlternativeImage filename="OCR-D-BIN-DENOISE/FILE_0012_OCR-D-BIN-DENOISE.IMG-DEN.png" comments=",cropped,binarized,despeckled"/>
        <pc:AlternativeImage filename="OCR-D-BIN-DENOISE-DESKEW/FILE_0012_OCR-D-BIN-DENOISE-DESKEW.IMG-DESKEW.png" comments=",cropped,binarized,despeckled,deskewed"/>
        <pc:AlternativeImage filename="OCR-D-SEG/FILE_0012_OCR-D-SEG.IMG-CLIP.png" comments=",cropped,binarized,despeckled,deskewed,clipped"/>
        <pc:Border>
            <pc:Coords points="45,45 692,45 692,1094 45,1094"/>
        </pc:Border>
        <pc:ReadingOrder>
            <pc:OrderedGroup id="reading-order">
                <pc:RegionRefIndexed index="0" regionRef="FILE_0012_OCR-D-BIN-DENOISE-DESKEW_region0001"/>
                <pc:RegionRefIndexed index="1" regionRef="FILE_0012_OCR-D-BIN-DENOISE-DESKEW_region0002"/>
                <pc:RegionRefIndexed index="2" regionRef="FILE_0012_OCR-D-BIN-DENOISE-DESKEW_region0003"/>
            </pc:OrderedGroup>
        </pc:ReadingOrder>
        <pc:TextRegion id="FILE_0012_OCR-D-BIN-DENOISE-DESKEW_region0001">
            <pc:Coords points="107,51 62,52 51,64 50,323 53,466 56,470 168,471 625,445 692,439 692,53 632,48 553,47"/>
            <pc:TextLine id="FILE_0012_OCR-D-BIN-DENOISE-DESKEW_region0001_line0001">
                <pc:AlternativeImage filename="OCR-D-SEG-LINE-RESEG-DEWARP/FILE_0012_OCR-D-SEG-LINE-RESEG-DEWARP_FILE_0012_OCR-D-BIN-DENOISE-DESKEW_region0001_FILE_0012_OCR-D-BIN-DENOISE-DESKEW_region0001_line0001.IMG-DEWARP.png" comments="binarized,despeckled,dewarped"/>
                <pc:Coords points="150,50 145,56 76,56 62,52 51,64 50,82 55,87 66,89 108,87 118,91 135,88 158,89 162,86 190,88 196,85 237,84 282,89 305,85 399,87 413,84 491,83 517,86 577,83 586,87 674,85 692,87 692,53 637,53 627,48 544,53 534,52 529,47 520,47 513,51 508,48 486,49 474,54 438,54 430,53 425,48 416,48 411,53 379,52 374,48 371,48 357,52 334,49 324,54 289,55 268,50 247,53 222,50 218,50 178,50 169,54 164,50"/>
                <pc:TextEquiv conf="0.972681879997253">
                    <pc:Unicode>da grße Mittel zu erblicken, das endlich zur Loſung</pc:Unicode>
                </pc:TextEquiv>
            </pc:TextLine>
            <pc:TextLine id="FILE_0012_OCR-D-BIN-DENOISE-DESKEW_region0001_line0002">
                <pc:AlternativeImage filename="OCR-D-SEG-LINE-RESEG-DEWARP/FILE_0012_OCR-D-SEG-LINE-RESEG-DEWARP_FILE_0012_OCR-D-BIN-DENOISE-DESKEW_region0001_FILE_0012_OCR-D-BIN-DENOISE-DESKEW_region0001_line0002.IMG-DEWARP.png" comments="binarized,despeckled,dewarped"/>
                <pc:Coords points="196,86 190,89 162,87 158,90 135,89 123,92 108,88 55,88 50,94 50,114 57,121 73,118 81,122 109,121 118,117 174,117 214,122 247,117 255,117 262,121 286,119 306,122 335,117 344,120 421,116 458,120 463,117 506,118 510,115 547,114 573,120 581,118 610,121 640,114 666,119 692,118 692,88 674,86 620,88 586,88 577,84 517,87 491,84 456,84 413,85 399,88 305,86 282,90 237,85"/>
                <pc:TextEquiv conf="0.950729548931122">
                    <pc:Unicode>der ſecialen Frage fuhren wud Dieſe Loſung muß</pc:Unicode>
                </pc:TextEquiv>
            </pc:TextLine>
            <pc:TextLine id="FILE_0012_OCR-D-BIN-DENOISE-DESKEW_region0001_line0003">
                <pc:AlternativeImage filename="OCR-D-SEG-LINE-RESEG-DEWARP/FILE_0012_OCR-D-SEG-LINE-RESEG-DEWARP_FILE_0012_OCR-D-BIN-DENOISE-DESKEW_region0001_FILE_0012_OCR-D-BIN-DENOISE-DESKEW_region0001_line0003.IMG-DEWARP.png" comments="binarized,despeckled,dewarped"/>
                <pc:Coords points="68,119 58,122 50,129 50,146 56,151 183,151 217,154 227,151 238,153 249,149 305,154 360,151 390,152 396,148 405,148 460,152 467,156 485,152 533,154 562,151 577,156 620,149 692,149 692,119 666,120 643,115 604,122 581,119 573,121 547,115 510,116 506,119 463,118 458,121 421,117 382,120 344,121 335,118 307,123 286,120 262,122 255,118 214,123 174,118 118,118 109,122 81,123"/>
                <pc:TextEquiv conf="0.979434788227081">
                    <pc:Unicode>aber der Loſung der großen polltiſchen Fragen der</pc:Unicode>
                </pc:TextEquiv>
            </pc:TextLine>
            <pc:TextLine id="FILE_0012_OCR-D-BIN-DENOISE-DESKEW_region0001_line0004">
                <pc:AlternativeImage filename="OCR-D-SEG-LINE-RESEG-DEWARP/FILE_0012_OCR-D-SEG-LINE-RESEG-DEWARP_FILE_0012_OCR-D-BIN-DENOISE-DESKEW_region0001_FILE_0012_OCR-D-BIN-DENOISE-DESKEW_region0001_line0004.IMG-DEWARP.png" comments="binarized,despeckled,dewarped"/>
                <pc:Coords points="57,152 51,158 52,177 63,186 75,187 128,181 178,181 209,185 255,181 365,180 373,184 386,184 413,180 451,181 463,174 463,155 460,153 405,149 396,149 390,153 360,152 332,155 249,150 238,154 231,152 217,155 183,152"/>
                <pc:TextEquiv conf="0.973861277103424">
                    <pc:Unicode>Gegenwart unbedingt vorausgehen</pc:Unicode>
                </pc:TextEquiv>
            </pc:TextLine>
            <pc:TextLine id="FILE_0012_OCR-D-BIN-DENOISE-DESKEW_region0001_line0005">
                <pc:AlternativeImage filename="OCR-D-SEG-LINE-RESEG-DEWARP/FILE_0012_OCR-D-SEG-LINE-RESEG-DEWARP_FILE_0012_OCR-D-BIN-DENOISE-DESKEW_region0001_FILE_0012_OCR-D-BIN-DENOISE-DESKEW_region0001_line0005.IMG-DEWARP.png" comments="binarized,despeckled,dewarped"/>
                <pc:Coords points="460,178 451,182 413,181 386,185 373,185 365,181 255,182 209,186 178,182 128,182 99,187 83,186 79,188 79,213 95,218 111,214 190,214 220,217 354,214 357,217 364,217 413,212 435,213 440,217 461,217 478,213 577,217 692,214 692,181 641,181 636,177 625,177 619,182 592,183 580,178 566,180 562,177 549,177 544,182 500,183"/>
                <pc:TextEquiv conf="0.986823618412018">
                    <pc:Unicode>Mit kleinen Mittelchen behilft man ſich auch n</pc:Unicode>
                </pc:TextEquiv>
            </pc:TextLine>
            <pc:TextLine id="FILE_0012_OCR-D-BIN-DENOISE-DESKEW_region0001_line0006">
                <pc:AlternativeImage filename="OCR-D-SEG-LINE-RESEG-DEWARP/FILE_0012_OCR-D-SEG-LINE-RESEG-DEWARP_FILE_0012_OCR-D-BIN-DENOISE-DESKEW_region0001_FILE_0012_OCR-D-BIN-DENOISE-DESKEW_region0001_line0006.IMG-DEWARP.png" comments="binarized,despeckled,dewarped"/>
                <pc:Coords points="62,213 51,222 50,235 50,243 55,248 112,247 121,251 143,246 198,251 211,247 268,249 284,245 298,248 396,245 408,249 449,248 455,245 467,248 538,244 547,248 565,245 605,248 692,245 692,215 577,218 478,214 461,218 440,218 435,214 413,213 364,218 357,218 354,215 220,218 190,215 111,215 95,219 77,213"/>
                <pc:TextEquiv conf="0.988816380500793">
                    <pc:Unicode>Betreff der lezteren, wahrend auch hier Alles zu einer um</pc:Unicode>
                </pc:TextEquiv>
            </pc:TextLine>
            <pc:TextLine id="FILE_0012_OCR-D-BIN-DENOISE-DESKEW_region0001_line0007">
                <pc:AlternativeImage filename="OCR-D-SEG-LINE-RESEG-DEWARP/FILE_0012_OCR-D-SEG-LINE-RESEG-DEWARP_FILE_0012_OCR-D-BIN-DENOISE-DESKEW_region0001_FILE_0012_OCR-D-BIN-DENOISE-DESKEW_region0001_line0007.IMG-DEWARP.png" comments="binarized,despeckled,dewarped"/>
                <pc:Coords points="56,248 50,253 50,277 56,283 79,285 138,278 187,284 231,282 237,278 266,277 275,281 297,277 302,280 331,282 355,278 455,277 464,280 502,276 614,280 651,279 657,276 670,279 692,278 692,246 605,249 565,246 547,249 538,245 509,248 467,249 455,246 449,249 408,250 396,246 298,249 284,246 268,250 211,248 198,252 143,247 121,252 112,248 94,251"/>
                <pc:TextEquiv conf="0.977277040481567">
                    <pc:Unicode>faſſenden Neugeſtaltung drängt die der modernen Cwiliſation und</pc:Unicode>
                </pc:TextEquiv>
            </pc:TextLine>
            <pc:TextLine id="FILE_0012_OCR-D-BIN-DENOISE-DESKEW_region0001_line0008">
                <pc:AlternativeImage filename="OCR-D-SEG-LINE-RESEG-DEWARP/FILE_0012_OCR-D-SEG-LINE-RESEG-DEWARP_FILE_0012_OCR-D-BIN-DENOISE-DESKEW_region0001_FILE_0012_OCR-D-BIN-DENOISE-DESKEW_region0001_line0008.IMG-DEWARP.png" comments="binarized,despeckled,dewarped"/>
                <pc:Coords points="138,279 86,286 55,284 51,291 51,308 58,315 122,314 136,311 139,314 150,315 163,311 220,313 234,310 286,312 403,309 437,313 552,309 637,313 692,311 692,280 670,280 664,277 651,280 614,281 562,280 545,277 480,281 455,278 355,279 331,283 302,281 297,278 283,282 266,278 237,279 231,283 187,285"/>
                <pc:TextEquiv conf="0.969769060611725">
                    <pc:Unicode>dem allgemeinen Friedensbedurfniß der Volk Curopa's</pc:Unicode>
                </pc:TextEquiv>
            </pc:TextLine>
            <pc:TextLine id="FILE_0012_OCR-D-BIN-DENOISE-DESKEW_region0001_line0009">
                <pc:AlternativeImage filename="OCR-D-SEG-LINE-RESEG-DEWARP/FILE_0012_OCR-D-SEG-LINE-RESEG-DEWARP_FILE_0012_OCR-D-BIN-DENOISE-DESKEW_region0001_FILE_0012_OCR-D-BIN-DENOISE-DESKEW_region0001_line0009.IMG-DEWARP.png" comments="binarized,despeckled,dewarped"/>
                <pc:Coords points="227,311 220,314 163,312 150,316 139,315 136,312 122,315 59,316 51,325 51,339 55,343 63,342 71,347 96,349 133,348 152,343 234,343 261,345 280,342 328,342 335,345 395,342 448,345 481,345 488,342 515,344 522,340 559,340 576,344 690,343 692,341 692,312 637,314 590,311 573,313 562,310 437,314 403,310 286,313"/>
                <pc:TextEquiv conf="0.961687088012695">
                    <pc:Unicode>entſpricht Das Syſtem des Militarismus und der ein</pc:Unicode>
                </pc:TextEquiv>
            </pc:TextLine>
            <pc:TextLine id="FILE_0012_OCR-D-BIN-DENOISE-DESKEW_region0001_line0010">
                <pc:AlternativeImage filename="OCR-D-SEG-LINE-RESEG-DEWARP/FILE_0012_OCR-D-SEG-LINE-RESEG-DEWARP_FILE_0012_OCR-D-BIN-DENOISE-DESKEW_region0001_FILE_0012_OCR-D-BIN-DENOISE-DESKEW_region0001_line0010.IMG-DEWARP.png" comments="binarized,despeckled,dewarped"/>
                <pc:Coords points="56,343 51,348 53,371 63,379 73,380 188,378 201,375 228,375 234,378 338,374 356,378 420,373 449,377 541,374 606,378 692,376 692,344 576,345 559,341 522,341 515,345 501,345 495,342 481,346 448,346 395,343 335,346 328,343 280,343 264,346 234,344 152,344 133,349 96,350 71,348 67,344"/>
                <pc:TextEquiv conf="0.954797387123108">
                    <pc:Unicode>feitigen Selbſthilfe be internationalen Streitigkeiten,</pc:Unicode>
                </pc:TextEquiv>
            </pc:TextLine>
            <pc:TextLine id="FILE_0012_OCR-D-BIN-DENOISE-DESKEW_region0001_line0011">
                <pc:AlternativeImage filename="OCR-D-SEG-LINE-RESEG-DEWARP/FILE_0012_OCR-D-SEG-LINE-RESEG-DEWARP_FILE_0012_OCR-D-BIN-DENOISE-DESKEW_region0001_FILE_0012_OCR-D-BIN-DENOISE-DESKEW_region0001_line0011.IMG-DEWARP.png" comments="binarized,despeckled,dewarped"/>
                <pc:Coords points="201,376 188,379 64,382 57,389 56,400 64,408 81,411 88,408 147,407 169,410 307,407 321,411 369,410 375,405 404,405 420,409 549,405 575,411 597,406 607,409 636,408 644,405 692,406 692,377 606,379 541,375 449,378 420,374 356,379 338,375 234,379 228,376"/>
                <pc:TextEquiv conf="0.949009776115417">
                    <pc:Unicode>— mit einem Worte die Fauſtrechts oder Krtegs</pc:Unicode>
                </pc:TextEquiv>
            </pc:TextLine>
            <pc:TextLine id="FILE_0012_OCR-D-BIN-DENOISE-DESKEW_region0001_line0012">
                <pc:AlternativeImage filename="OCR-D-SEG-LINE-RESEG-DEWARP/FILE_0012_OCR-D-SEG-LINE-RESEG-DEWARP_FILE_0012_OCR-D-BIN-DENOISE-DESKEW_region0001_FILE_0012_OCR-D-BIN-DENOISE-DESKEW_region0001_line0012.IMG-DEWARP.png" comments="binarized,despeckled,dewarped"/>
                <pc:Coords points="88,409 81,412 64,412 53,421 53,436 61,444 528,440 587,442 605,446 636,444 659,439 692,439 692,407 644,406 636,409 607,410 597,407 575,412 549,406 420,410 404,406 375,406 369,411 321,412 307,408 169,411 147,408"/>
                <pc:TextEquiv conf="0.967938780784607">
                    <pc:Unicode>muß Seitens der ewilinten Staaten endlich aufgegeben</pc:Unicode>
                </pc:TextEquiv>
            </pc:TextLine>
            <pc:TextLine id="FILE_0012_OCR-D-BIN-DENOISE-DESKEW_region0001_line0013">
                <pc:AlternativeImage filename="OCR-D-SEG-LINE-RESEG-DEWARP/FILE_0012_OCR-D-SEG-LINE-RESEG-DEWARP_FILE_0012_OCR-D-BIN-DENOISE-DESKEW_region0001_FILE_0012_OCR-D-BIN-DENOISE-DESKEW_region0001_line0013.IMG-DEWARP.png" comments="binarized,despeckled,dewarped"/>
                <pc:Coords points="94,443 61,445 53,453 53,467 55,469 56,470 158,470 161,467 161,448 156,443"/>
                <pc:TextEquiv conf="0.898010492324829">
                    <pc:Unicode>werden</pc:Unicode>
                </pc:TextEquiv>
            </pc:TextLine>
            <pc:TextEquiv>
                <pc:Unicode>da grße Mittel zu erblicken, das endlich zur Loſung
der ſecialen Frage fuhren wud Dieſe Loſung muß
aber der Loſung der großen polltiſchen Fragen der
Gegenwart unbedingt vorausgehen
Mit kleinen Mittelchen behilft man ſich auch n
Betreff der lezteren, wahrend auch hier Alles zu einer um
faſſenden Neugeſtaltung drängt die der modernen Cwiliſation und
dem allgemeinen Friedensbedurfniß der Volk Curopa's
entſpricht Das Syſtem des Militarismus und der ein
feitigen Selbſthilfe be internationalen Streitigkeiten,
— mit einem Worte die Fauſtrechts oder Krtegs
muß Seitens der ewilinten Staaten endlich aufgegeben
werden</pc:Unicode>
            </pc:TextEquiv>
        </pc:TextRegion>
        <pc:TextRegion id="FILE_0012_OCR-D-BIN-DENOISE-DESKEW_region0002">
            <pc:Coords points="152,472 79,475 52,518 58,1018 62,1021 692,1016 692,471 653,468"/>
            <pc:TextLine id="FILE_0012_OCR-D-BIN-DENOISE-DESKEW_region0002_line0001">
                <pc:AlternativeImage filename="OCR-D-SEG-LINE-RESEG-DEWARP/FILE_0012_OCR-D-SEG-LINE-RESEG-DEWARP_FILE_0012_OCR-D-BIN-DENOISE-DESKEW_region0002_FILE_0012_OCR-D-BIN-DENOISE-DESKEW_region0002_line0001.IMG-DEWARP.png" comments="binarized,despeckled,dewarped"/>
                <pc:Coords points="221,472 201,475 99,474 81,474 78,476 77,478 77,494 80,505 85,508 129,504 169,504 197,508 206,505 227,508 294,504 328,508 397,502 403,505 462,504 478,507 538,502 559,505 589,503 621,507 647,503 692,503 692,472 650,472 647,468 644,468 615,469 608,473 539,473 524,469 507,469 505,472 501,469 483,469 451,470 446,474 393,473 390,470 377,470 375,473 368,470 343,470 316,471 314,474 282,475 264,474 262,471 254,471"/>
                <pc:TextEquiv conf="0.967935085296631">
                    <pc:Unicode>Die verſchtedenen Friedensgeſellſchaften verfolgen</pc:Unicode>
                </pc:TextEquiv>
            </pc:TextLine>
            <pc:TextLine id="FILE_0012_OCR-D-BIN-DENOISE-DESKEW_region0002_line0002">
                <pc:AlternativeImage filename="OCR-D-SEG-LINE-RESEG-DEWARP/FILE_0012_OCR-D-SEG-LINE-RESEG-DEWARP_FILE_0012_OCR-D-BIN-DENOISE-DESKEW_region0002_FILE_0012_OCR-D-BIN-DENOISE-DESKEW_region0002_line0002.IMG-DEWARP.png" comments="binarized,despeckled,dewarped"/>
                <pc:Coords points="64,503 55,511 53,516 53,532 58,538 71,540 152,537 163,540 178,537 183,540 202,539 206,542 225,541 231,537 244,539 379,535 391,539 466,537 489,540 555,535 569,538 607,536 614,539 633,537 638,534 692,534 692,506 659,504 628,505 621,508 589,504 559,506 544,503 495,507 462,505 422,507 403,506 397,503 328,509 294,505 251,505 234,509 206,506 197,509 169,505 129,505 85,509 70,507"/>
                <pc:TextEquiv conf="0.948117792606354">
                    <pc:Unicode>den loblichen Zweck diſes Mißverhaltni dadurch zu be—</pc:Unicode>
                </pc:TextEquiv>
            </pc:TextLine>
            <pc:TextLine id="FILE_0012_OCR-D-BIN-DENOISE-DESKEW_region0002_line0003">
                <pc:AlternativeImage filename="OCR-D-SEG-LINE-RESEG-DEWARP/FILE_0012_OCR-D-SEG-LINE-RESEG-DEWARP_FILE_0012_OCR-D-BIN-DENOISE-DESKEW_region0002_FILE_0012_OCR-D-BIN-DENOISE-DESKEW_region0002_line0003.IMG-DEWARP.png" comments="binarized,despeckled,dewarped"/>
                <pc:Coords points="59,539 53,548 54,566 59,573 184,571 235,574 385,568 414,569 422,572 499,567 524,570 608,569 634,571 672,566 692,568 692,540 669,536 638,535 633,538 614,540 607,537 569,539 555,536 489,541 466,538 391,540 379,536 253,540 231,538 225,542 206,543 202,540 183,541 178,538 163,541 152,538 111,542"/>
                <pc:TextEquiv conf="0.923190057277679">
                    <pc:Unicode>ſeitigen, daß ſie fir die Schlichtung imternationaler Conflitt</pc:Unicode>
                </pc:TextEquiv>
            </pc:TextLine>
            <pc:TextLine id="FILE_0012_OCR-D-BIN-DENOISE-DESKEW_region0002_line0004">
                <pc:AlternativeImage filename="OCR-D-SEG-LINE-RESEG-DEWARP/FILE_0012_OCR-D-SEG-LINE-RESEG-DEWARP_FILE_0012_OCR-D-BIN-DENOISE-DESKEW_region0002_FILE_0012_OCR-D-BIN-DENOISE-DESKEW_region0002_line0004.IMG-DEWARP.png" comments="binarized,despeckled,dewarped"/>
                <pc:Coords points="69,572 59,574 55,580 55,598 60,603 83,606 169,602 187,603 194,607 216,602 238,602 287,606 353,601 360,604 430,603 445,606 576,600 611,603 622,598 692,599 692,569 672,567 634,572 608,570 524,571 499,568 422,573 414,570 385,569 235,575 184,572 83,575"/>
                <pc:TextEquiv conf="0.944047033786774">
                    <pc:Unicode>durch jeweilig emzuſetzende Schiedsgertchte eintreten und</pc:Unicode>
                </pc:TextEquiv>
            </pc:TextLine>
            <pc:TextLine id="FILE_0012_OCR-D-BIN-DENOISE-DESKEW_region0002_line0005">
                <pc:AlternativeImage filename="OCR-D-SEG-LINE-RESEG-DEWARP/FILE_0012_OCR-D-SEG-LINE-RESEG-DEWARP_FILE_0012_OCR-D-BIN-DENOISE-DESKEW_region0002_FILE_0012_OCR-D-BIN-DENOISE-DESKEW_region0002_line0005.IMG-DEWARP.png" comments="binarized,despeckled,dewarped"/>
                <pc:Coords points="60,604 54,613 54,630 59,635 100,634 114,634 120,638 167,634 178,634 186,638 204,634 251,633 348,638 438,633 515,635 569,633 577,636 621,631 692,632 692,603 681,603 673,599 622,599 611,604 576,601 445,607 430,604 360,605 353,602 287,607 238,603 216,603 194,608 187,604 169,603 139,606 117,603 111,607"/>
                <pc:TextEquiv conf="0.942449033260345">
                    <pc:Unicode>die offentliche Meimung dafur zu erwarmen ſuchen Di</pc:Unicode>
                </pc:TextEquiv>
            </pc:TextLine>
            <pc:TextLine id="FILE_0012_OCR-D-BIN-DENOISE-DESKEW_region0002_line0006">
                <pc:AlternativeImage filename="OCR-D-SEG-LINE-RESEG-DEWARP/FILE_0012_OCR-D-SEG-LINE-RESEG-DEWARP_FILE_0012_OCR-D-BIN-DENOISE-DESKEW_region0002_FILE_0012_OCR-D-BIN-DENOISE-DESKEW_region0002_line0006.IMG-DEWARP.png" comments="binarized,despeckled,dewarped"/>
                <pc:Coords points="97,635 60,636 54,642 55,662 60,667 70,669 99,670 123,666 132,671 169,666 229,666 235,669 268,665 309,665 319,668 339,665 431,664 437,667 491,670 523,669 557,664 574,667 601,664 606,669 692,664 692,633 663,632 621,632 592,637 569,634 491,637 449,634 348,639 251,634 204,635 190,639 167,635 120,639 114,635"/>
                <pc:TextEquiv conf="0.961913764476776">
                    <pc:Unicode>Anhänger des Militarismus machen dem gegenubtr geltend</pc:Unicode>
                </pc:TextEquiv>
            </pc:TextLine>
            <pc:TextLine id="FILE_0012_OCR-D-BIN-DENOISE-DESKEW_region0002_line0007">
                <pc:AlternativeImage filename="OCR-D-SEG-LINE-RESEG-DEWARP/FILE_0012_OCR-D-SEG-LINE-RESEG-DEWARP_FILE_0012_OCR-D-BIN-DENOISE-DESKEW_region0002_FILE_0012_OCR-D-BIN-DENOISE-DESKEW_region0002_line0007.IMG-DEWARP.png" comments="binarized,despeckled,dewarped"/>
                <pc:Coords points="61,668 55,677 55,695 61,700 86,703 110,703 123,698 187,698 218,702 388,697 404,700 470,702 499,696 523,696 557,697 567,700 576,697 591,699 598,691 626,697 692,697 692,666 623,667 592,675 585,668 568,665 523,670 491,671 437,668 431,665 339,666 328,669 309,666 268,666 250,669 235,670 229,667 169,667 135,672 123,667 99,671"/>
                <pc:TextEquiv conf="0.960827887058258">
                    <pc:Unicode>daß keine Gromacht di Cntſcheidung uber ihie eigenen</pc:Unicode>
                </pc:TextEquiv>
            </pc:TextLine>
            <pc:TextLine id="FILE_0012_OCR-D-BIN-DENOISE-DESKEW_region0002_line0008">
                <pc:AlternativeImage filename="OCR-D-SEG-LINE-RESEG-DEWARP/FILE_0012_OCR-D-SEG-LINE-RESEG-DEWARP_FILE_0012_OCR-D-BIN-DENOISE-DESKEW_region0002_FILE_0012_OCR-D-BIN-DENOISE-DESKEW_region0002_line0008.IMG-DEWARP.png" comments="binarized,despeckled,dewarped"/>
                <pc:Coords points="123,699 110,704 61,701 56,706 56,730 60,734 74,735 118,730 160,734 194,733 199,730 219,733 249,729 274,732 292,729 304,733 326,734 350,733 356,730 386,733 411,729 485,732 550,731 563,728 569,731 595,731 604,722 612,722 621,731 692,730 692,697 611,697 607,704 597,704 586,698 565,701 557,698 499,697 469,703 404,701 388,698 218,703 187,699"/>
                <pc:TextEquiv conf="0.971833169460297">
                    <pc:Unicode>Jntereſſen, ſoweit es ſich nicht um unbedeutende Dinge</pc:Unicode>
                </pc:TextEquiv>
            </pc:TextLine>
            <pc:TextLine id="FILE_0012_OCR-D-BIN-DENOISE-DESKEW_region0002_line0009">
                <pc:AlternativeImage filename="OCR-D-SEG-LINE-RESEG-DEWARP/FILE_0012_OCR-D-SEG-LINE-RESEG-DEWARP_FILE_0012_OCR-D-BIN-DENOISE-DESKEW_region0002_FILE_0012_OCR-D-BIN-DENOISE-DESKEW_region0002_line0009.IMG-DEWARP.png" comments="binarized,despeckled,dewarped"/>
                <pc:Coords points="118,731 94,733 88,736 61,735 56,741 56,760 63,767 126,763 152,765 164,761 196,761 253,765 271,761 290,761 340,766 349,763 395,760 410,760 416,763 460,761 514,764 523,759 602,763 632,759 692,760 692,731 620,732 608,744 597,732 569,732 563,729 550,732 411,730 386,734 356,731 350,734 326,735 304,734 292,730 274,733 261,730 225,734 199,731 184,735"/>
                <pc:TextEquiv conf="0.957231044769287">
                    <pc:Unicode>handelt, aus den Handen geben oder den ewetligen zu er</pc:Unicode>
                </pc:TextEquiv>
            </pc:TextLine>
            <pc:TextLine id="FILE_0012_OCR-D-BIN-DENOISE-DESKEW_region0002_line0010">
                <pc:AlternativeImage filename="OCR-D-SEG-LINE-RESEG-DEWARP/FILE_0012_OCR-D-SEG-LINE-RESEG-DEWARP_FILE_0012_OCR-D-BIN-DENOISE-DESKEW_region0002_FILE_0012_OCR-D-BIN-DENOISE-DESKEW_region0002_line0010.IMG-DEWARP.png" comments="binarized,despeckled,dewarped"/>
                <pc:Coords points="164,762 152,766 126,764 63,768 56,775 57,790 65,798 93,795 124,797 167,794 207,798 236,793 249,795 315,793 387,795 391,792 435,792 453,795 480,793 549,795 563,791 592,794 692,794 692,759 602,764 523,760 514,765 460,762 416,764 410,761 395,761 349,764 340,767 290,762 271,762 253,766 228,763 210,765 196,762"/>
                <pc:TextEquiv conf="0.967975854873657">
                    <pc:Unicode>nennenden Schuedsrichtern uberlaſſen konn Jn der That</pc:Unicode>
                </pc:TextEquiv>
            </pc:TextLine>
            <pc:TextLine id="FILE_0012_OCR-D-BIN-DENOISE-DESKEW_region0002_line0011">
                <pc:AlternativeImage filename="OCR-D-SEG-LINE-RESEG-DEWARP/FILE_0012_OCR-D-SEG-LINE-RESEG-DEWARP_FILE_0012_OCR-D-BIN-DENOISE-DESKEW_region0002_FILE_0012_OCR-D-BIN-DENOISE-DESKEW_region0002_line0011.IMG-DEWARP.png" comments="binarized,despeckled,dewarped"/>
                <pc:Coords points="231,794 207,799 167,795 125,798 93,796 66,799 57,808 57,822 62,827 72,829 153,826 159,829 177,829 194,826 200,829 234,829 318,824 346,828 412,825 443,829 496,824 510,828 539,823 596,824 626,827 640,823 692,825 692,795 592,795 563,792 549,796 480,794 453,796 435,793 391,793 387,796 315,794 249,796"/>
                <pc:TextEquiv conf="0.929423034191132">
                    <pc:Unicode>wird auch durch uin bloßesgerlcht s ſyſtem,</pc:Unicode>
                </pc:TextEquiv>
            </pc:TextLine>
            <pc:TextLine id="FILE_0012_OCR-D-BIN-DENOISE-DESKEW_region0002_line0012">
                <pc:AlternativeImage filename="OCR-D-SEG-LINE-RESEG-DEWARP/FILE_0012_OCR-D-SEG-LINE-RESEG-DEWARP_FILE_0012_OCR-D-BIN-DENOISE-DESKEW_region0002_FILE_0012_OCR-D-BIN-DENOISE-DESKEW_region0002_line0012.IMG-DEWARP.png" comments="binarized,despeckled,dewarped"/>
                <pc:Coords points="281,825 234,830 200,830 194,827 177,830 159,830 153,827 63,828 56,837 56,851 56,854 62,859 101,862 130,858 173,858 188,861 254,857 340,860 367,856 466,860 503,855 567,856 582,859 692,855 692,826 640,824 626,828 596,825 539,824 510,829 499,825 443,830 412,826 346,829 318,825"/>
                <pc:TextEquiv conf="0.957729995250702">
                    <pc:Unicode>deſſen Annahme dem Belieben dei enzelnen Machte uber</pc:Unicode>
                </pc:TextEquiv>
            </pc:TextLine>
            <pc:TextLine id="FILE_0012_OCR-D-BIN-DENOISE-DESKEW_region0002_line0013">
                <pc:AlternativeImage filename="OCR-D-SEG-LINE-RESEG-DEWARP/FILE_0012_OCR-D-SEG-LINE-RESEG-DEWARP_FILE_0012_OCR-D-BIN-DENOISE-DESKEW_region0002_FILE_0012_OCR-D-BIN-DENOISE-DESKEW_region0002_line0013.IMG-DEWARP.png" comments="binarized,despeckled,dewarped"/>
                <pc:Coords points="64,859 56,864 56,869 57,886 65,894 80,895 92,895 96,892 132,893 147,889 208,890 227,893 249,888 260,891 283,889 307,894 354,890 366,893 386,889 487,889 494,891 515,891 529,888 580,894 627,888 692,889 692,856 582,860 567,857 503,856 466,861 367,857 340,861 266,858 188,862 173,859 130,859 101,863"/>
                <pc:TextEquiv conf="0.982348144054413">
                    <pc:Unicode>laſſen bleibt der Krieg nicht aus der Welt geſchafft</pc:Unicode>
                </pc:TextEquiv>
            </pc:TextLine>
            <pc:TextLine id="FILE_0012_OCR-D-BIN-DENOISE-DESKEW_region0002_line0014">
                <pc:AlternativeImage filename="OCR-D-SEG-LINE-RESEG-DEWARP/FILE_0012_OCR-D-SEG-LINE-RESEG-DEWARP_FILE_0012_OCR-D-BIN-DENOISE-DESKEW_region0002_FILE_0012_OCR-D-BIN-DENOISE-DESKEW_region0002_line0014.IMG-DEWARP.png" comments="binarized,despeckled,dewarped"/>
                <pc:Coords points="147,890 132,894 65,895 58,904 58,917 67,926 94,923 203,925 213,922 233,927 262,923 352,924 358,921 392,925 422,921 523,924 632,919 692,922 692,890 627,889 580,895 529,889 515,892 494,892 487,890 386,890 366,894 354,891 307,895 283,890 260,892 249,889 227,894 208,891"/>
                <pc:TextEquiv conf="0.922960937023163">
                    <pc:Unicode>werden Dieſes Zil tſt vtelmeh nur duch eme volker</pc:Unicode>
                </pc:TextEquiv>
            </pc:TextLine>
            <pc:TextLine id="FILE_0012_OCR-D-BIN-DENOISE-DESKEW_region0002_line0015">
                <pc:AlternativeImage filename="OCR-D-SEG-LINE-RESEG-DEWARP/FILE_0012_OCR-D-SEG-LINE-RESEG-DEWARP_FILE_0012_OCR-D-BIN-DENOISE-DESKEW_region0002_FILE_0012_OCR-D-BIN-DENOISE-DESKEW_region0002_line0015.IMG-DEWARP.png" comments="binarized,despeckled,dewarped"/>
                <pc:Coords points="94,924 67,927 59,935 59,951 66,958 94,956 99,959 198,958 212,955 226,955 232,958 404,954 446,958 481,953 692,953 692,923 666,920 532,925 422,922 392,926 358,922 352,925 262,924 233,928 213,923 203,926"/>
                <pc:TextEquiv conf="0.921018779277802">
                    <pc:Unicode>rechtlich zu ſanetlontrende, allgemetn verbindliche</pc:Unicode>
                </pc:TextEquiv>
            </pc:TextLine>
            <pc:TextLine id="FILE_0012_OCR-D-BIN-DENOISE-DESKEW_region0002_line0016">
                <pc:AlternativeImage filename="OCR-D-SEG-LINE-RESEG-DEWARP/FILE_0012_OCR-D-SEG-LINE-RESEG-DEWARP_FILE_0012_OCR-D-BIN-DENOISE-DESKEW_region0002_FILE_0012_OCR-D-BIN-DENOISE-DESKEW_region0002_line0016.IMG-DEWARP.png" comments="binarized,despeckled,dewarped"/>
                <pc:Coords points="85,957 67,959 59,968 59,983 67,991 165,990 191,987 233,987 245,990 274,986 323,986 344,989 486,988 493,984 502,983 518,987 645,984 692,986 692,954 481,954 446,959 404,955 232,959 226,956 212,956 198,959 99,960"/>
                <pc:TextEquiv conf="0.944664835929871">
                    <pc:Unicode>und regelmäßige nternatlonalt Gerichtsbarkeit</pc:Unicode>
                </pc:TextEquiv>
            </pc:TextLine>
            <pc:TextLine id="FILE_0012_OCR-D-BIN-DENOISE-DESKEW_region0002_line0017">
                <pc:AlternativeImage filename="OCR-D-SEG-LINE-RESEG-DEWARP/FILE_0012_OCR-D-SEG-LINE-RESEG-DEWARP_FILE_0012_OCR-D-BIN-DENOISE-DESKEW_region0002_FILE_0012_OCR-D-BIN-DENOISE-DESKEW_region0002_line0017.IMG-DEWARP.png" comments="binarized,despeckled,dewarped"/>
                <pc:Coords points="493,985 486,989 344,990 323,987 274,987 252,991 233,988 68,992 58,1002 58,1018 62,1021 692,1016 692,987 645,985 518,988"/>
                <pc:TextEquiv conf="0.948947489261627">
                    <pc:Unicode>zu erreichen Das Rechtsprineip muß endlich auch n</pc:Unicode>
                </pc:TextEquiv>
            </pc:TextLine>
            <pc:TextEquiv>
                <pc:Unicode>Die verſchtedenen Friedensgeſellſchaften verfolgen
den loblichen Zweck diſes Mißverhaltni dadurch zu be—
ſeitigen, daß ſie fir die Schlichtung imternationaler Conflitt
durch jeweilig emzuſetzende Schiedsgertchte eintreten und
die offentliche Meimung dafur zu erwarmen ſuchen Di
Anhänger des Militarismus machen dem gegenubtr geltend
daß keine Gromacht di Cntſcheidung uber ihie eigenen
Jntereſſen, ſoweit es ſich nicht um unbedeutende Dinge
handelt, aus den Handen geben oder den ewetligen zu er
nennenden Schuedsrichtern uberlaſſen konn Jn der That
wird auch durch uin bloßesgerlcht s ſyſtem,
deſſen Annahme dem Belieben dei enzelnen Machte uber
laſſen bleibt der Krieg nicht aus der Welt geſchafft
werden Dieſes Zil tſt vtelmeh nur duch eme volker
rechtlich zu ſanetlontrende, allgemetn verbindliche
und regelmäßige nternatlonalt Gerichtsbarkeit
zu erreichen Das Rechtsprineip muß endlich auch n</pc:Unicode>
            </pc:TextEquiv>
        </pc:TextRegion>
        <pc:TextRegion id="FILE_0012_OCR-D-BIN-DENOISE-DESKEW_region0003">
            <pc:Coords points="63,1022 60,1025 60,1082 69,1090 75,1091 655,1089 690,1085 692,1084 692,1025"/>
            <pc:TextLine id="FILE_0012_OCR-D-BIN-DENOISE-DESKEW_region0003_line0001">
                <pc:AlternativeImage filename="OCR-D-SEG-LINE-RESEG-DEWARP/FILE_0012_OCR-D-SEG-LINE-RESEG-DEWARP_FILE_0012_OCR-D-BIN-DENOISE-DESKEW_region0003_FILE_0012_OCR-D-BIN-DENOISE-DESKEW_region0003_line0001.IMG-DEWARP.png" comments="binarized,despeckled,dewarped"/>
                <pc:Coords points="63,1022 61,1034 69,1042 78,1042 88,1035 135,1033 149,1026 146,1022"/>
                <pc:TextEquiv conf="0.">
                    <pc:Unicode></pc:Unicode>
                </pc:TextEquiv>
            </pc:TextLine>
            <pc:TextLine id="FILE_0012_OCR-D-BIN-DENOISE-DESKEW_region0003_line0002">
                <pc:AlternativeImage filename="OCR-D-SEG-LINE-RESEG-DEWARP/FILE_0012_OCR-D-SEG-LINE-RESEG-DEWARP_FILE_0012_OCR-D-BIN-DENOISE-DESKEW_region0003_FILE_0012_OCR-D-BIN-DENOISE-DESKEW_region0003_line0002.IMG-DEWARP.png" comments="binarized,despeckled,dewarped"/>
                <pc:Coords points="366,1024 335,1029 315,1025 286,1025 281,1029 226,1030 221,1027 212,1027 206,1031 150,1026 135,1034 88,1036 78,1043 78,1051 83,1055 110,1055 115,1059 139,1057 153,1060 261,1056 343,1060 351,1056 366,1055 397,1057 692,1054 692,1026 521,1028 507,1024 497,1024 494,1028 446,1025 419,1028 403,1023 382,1023"/>
                <pc:TextEquiv conf="0.883536279201508">
                    <pc:Unicode>Vgl auch meime Schrift, De Anarchirmu nnd ds</pc:Unicode>
                </pc:TextEquiv>
            </pc:TextLine>
            <pc:TextLine id="FILE_0012_OCR-D-BIN-DENOISE-DESKEW_region0003_line0003">
                <pc:AlternativeImage filename="OCR-D-SEG-LINE-RESEG-DEWARP/FILE_0012_OCR-D-SEG-LINE-RESEG-DEWARP_FILE_0012_OCR-D-BIN-DENOISE-DESKEW_region0003_FILE_0012_OCR-D-BIN-DENOISE-DESKEW_region0003_line0003.IMG-DEWARP.png" comments="binarized,despeckled,dewarped"/>
                <pc:Coords points="70,1054 60,1063 60,1082 69,1090 99,1090 100,1090 117,1090 137,1088 543,1085 651,1089 689,1085 692,1082 692,1055 397,1058 366,1056 351,1057 343,1061 261,1057 153,1061 139,1058 115,1060 110,1056"/>
                <pc:TextEquiv conf="0.954072952270508">
                    <pc:Unicode>Recht der Schwachen ode Die drei Grundubel unferer Zeit'</pc:Unicode>
                </pc:TextEquiv>
            </pc:TextLine>
            <pc:TextEquiv>
                <pc:Unicode>
Vgl auch meime Schrift, De Anarchirmu nnd ds
Recht der Schwachen ode Die drei Grundubel unferer Zeit'</pc:Unicode>
            </pc:TextEquiv>
        </pc:TextRegion>
    </pc:Page>
</pc:PcGts>
